src/topsis.py
topsis_anubhav_102003049-1.0.2.dist-info/METADATA
topsis_anubhav_102003049-1.0.2.dist-info/WHEEL
topsis_anubhav_102003049-1.0.2.dist-info/entry_points.txt
topsis_anubhav_102003049-1.0.2.dist-info/top_level.txt
topsis_anubhav_102003049-1.0.2.dist-info/RECORD
