Metadata-Version: 2.1
Name: topsis-anubhav-102003049
Version: 1.0.2
Summary: A Python package implementing TOPSIS technique.
Home-page: UNKNOWN
Author: Anubhav Chawla
Author-email: anubhavchawla02@gmail.com
License: MIT
Platform: UNKNOWN
Classifier: License :: OSI Approved :: MIT License
Classifier: Programming Language :: Python :: 3
Classifier: Programming Language :: Python :: 3.4
Classifier: Programming Language :: Python :: 3.5
Classifier: Programming Language :: Python :: 3.6
Classifier: Programming Language :: Python :: 3.7
Requires-Dist: scipy
Requires-Dist: tabulate
Requires-Dist: numpy
Requires-Dist: pandas
